sitk_cli/__init__.py
sitk_cli/lib.py
sitk_cli-0.7.0.post1.dist-info/LICENSE
sitk_cli-0.7.0.post1.dist-info/METADATA
sitk_cli-0.7.0.post1.dist-info/WHEEL
sitk_cli-0.7.0.post1.dist-info/top_level.txt
sitk_cli-0.7.0.post1.dist-info/RECORD
