Metadata-Version: 2.1
Name: sitk-cli
Version: 0.7.0.post1
Summary: Wrap SimpleITK functions as command lines
Home-page: https://github.com/dyollb/sitk-cli
License: MIT License
Project-URL: Bug Tracker, https://github.com/dyollb/sitk-cli/issues
Project-URL: Source Code, https://github.com/dyollb/sitk-cli
License-File: LICENSE
Requires-Dist: makefun
Requires-Dist: SimpleITK
Requires-Dist: typer
Provides-Extra: dev
Requires-Dist: mypy ; extra == 'dev'
Requires-Dist: pytest ; extra == 'dev'
